strictus_dictus.py
strictus_dictus-0.0.12.dist-info/METADATA
strictus_dictus-0.0.12.dist-info/WHEEL
strictus_dictus-0.0.12.dist-info/top_level.txt
strictus_dictus-0.0.12.dist-info/RECORD
