Metadata-Version: 2.1
Name: strictus-dictus
Version: 0.0.12
Summary: Strictus Dictus
Home-page: https://github.com/jbasko/strictus-dictus
Author: Jazeps Basko
Author-email: jazeps.basko@gmail.com
Maintainer: Jazeps Basko
Maintainer-email: jazeps.basko@gmail.com
License: MIT
Keywords: dictionary schema attribute attrdict type hinting typing annotations
Platform: UNKNOWN
Classifier: Development Status :: 4 - Beta
Classifier: Intended Audience :: Developers
Classifier: Topic :: Software Development :: Libraries
Classifier: Programming Language :: Python
Classifier: Programming Language :: Python :: 3
Classifier: Programming Language :: Python :: 3.6
Classifier: Programming Language :: Python :: 3.7
Classifier: License :: OSI Approved :: MIT License
Requires-Python: >=3.6.0
Requires-Dist: typing-inspect
Requires-Dist: dataclasses; python_version=="3.6"
